[{"fileName":"%C4%BDudov%C3%ADt_Klein.json","fighterAnsiName":"Ludovit Klein","mmaStatsName":null},{"fileName":"Adrian_Yanez.json","fighterAnsiName":"Adrian Yanez","mmaStatsName":null},{"fileName":"Aleksandar_Raki%C4%87.json","fighterAnsiName":"Aleksandar Rakic","mmaStatsName":null},{"fileName":"Aleksei_Oleinik.json","fighterAnsiName":"Aleksei Oleinik","mmaStatsName":null},{"fileName":"Alex_Caceres.json","fighterAnsiName":"Alex Caceres","mmaStatsName":null},{"fileName":"Alex_Morono.json","fighterAnsiName":"Alex Morono","mmaStatsName":null},{"fileName":"Alex_Pereira.json","fighterAnsiName":"Alex Pereira","mmaStatsName":null},{"fileName":"Alex_Perez_(fighter).json","fighterAnsiName":"Alex Perez","mmaStatsName":null},{"fileName":"Alexa_Grasso.json","fighterAnsiName":"Alexa Grasso","mmaStatsName":null},{"fileName":"Alexander_Gustafsson.json","fighterAnsiName":"Alexander Gustafsson","mmaStatsName":null},{"fileName":"Alexander_Hernandez.json","fighterAnsiName":"Alexander Hernandez","mmaStatsName":null},{"fileName":"Alexander_Romanov_(fighter).json","fighterAnsiName":"Alexander Romanov","mmaStatsName":null},{"fileName":"Alexander_Volkanovski.json","fighterAnsiName":"Alexander Volkanovski","mmaStatsName":null},{"fileName":"Alexander_Volkov_(fighter).json","fighterAnsiName":"Alexander Volkov","mmaStatsName":null},{"fileName":"Alexandre_Pantoja.json","fighterAnsiName":"Alexandre Pantoja","mmaStatsName":null},{"fileName":"Aljamain_Sterling.json","fighterAnsiName":"Aljamain Sterling","mmaStatsName":null},{"fileName":"Alonzo_Menifield.json","fighterAnsiName":"Alonzo Menifield","mmaStatsName":null},{"fileName":"Amanda_Lemos.json","fighterAnsiName":"Amanda Lemos","mmaStatsName":null},{"fileName":"Amanda_Nunes.json","fighterAnsiName":"Amanda Nunes","mmaStatsName":null},{"fileName":"Amanda_Ribas.json","fighterAnsiName":"Amanda Ribas","mmaStatsName":null},{"fileName":"Amir_Albazi.json","fighterAnsiName":"Amir Albazi","mmaStatsName":null},{"fileName":"Andr%C3%A9_Fialho.json","fighterAnsiName":"Andre Fialho","mmaStatsName":null},{"fileName":"Andr%C3%A9_Muniz.json","fighterAnsiName":"Andre Muniz","mmaStatsName":null},{"fileName":"Andrea_Lee_(fighter).json","fighterAnsiName":"Andrea Lee","mmaStatsName":null},{"fileName":"Andrei_Arlovski.json","fighterAnsiName":"Andrei Arlovski","mmaStatsName":null},{"fileName":"Angela_Hill.json","fighterAnsiName":"Angela Hill","mmaStatsName":null},{"fileName":"Angela_Hill_(fighter).json","fighterAnsiName":"Angela Hill","mmaStatsName":null},{"fileName":"Anthony_Hernandez_(fighter).json","fighterAnsiName":"Anthony Hernandez","mmaStatsName":null},{"fileName":"Anthony_Smith_(fighter).json","fighterAnsiName":"Anthony Smith","mmaStatsName":null},{"fileName":"Ariane_Lipski.json","fighterAnsiName":"Ariane Lipski","mmaStatsName":null},{"fileName":"Arman_Tsarukyan.json","fighterAnsiName":"Arman Tsarukyan","mmaStatsName":null},{"fileName":"Arnold_Allen.json","fighterAnsiName":"Arnold Allen","mmaStatsName":null},{"fileName":"Aspen_Ladd.json","fighterAnsiName":"Aspen Ladd","mmaStatsName":null},{"fileName":"Augusto_Sakai.json","fighterAnsiName":"Augusto Sakai","mmaStatsName":null},{"fileName":"Austin_Lingo.json","fighterAnsiName":"Austin Lingo","mmaStatsName":null},{"fileName":"Belal_Muhammad.json","fighterAnsiName":"Belal Muhammad","mmaStatsName":null},{"fileName":"Beneil_Dariush.json","fighterAnsiName":"Beneil Dariush","mmaStatsName":null},{"fileName":"Beno%C3%AEt_Saint-Denis.json","fighterAnsiName":"Benoit Saint-Denis","mmaStatsName":null},{"fileName":"Blagoy_Ivanov.json","fighterAnsiName":"Blagoy Ivanov","mmaStatsName":null},{"fileName":"Bo_Nickal.json","fighterAnsiName":"Bo Nickal","mmaStatsName":null},{"fileName":"Bobby_Green.json","fighterAnsiName":"Bobby Green","mmaStatsName":null},{"fileName":"Brad_Tavares.json","fighterAnsiName":"Brad Tavares","mmaStatsName":null},{"fileName":"Brandon_Moreno.json","fighterAnsiName":"Brandon Moreno","mmaStatsName":null},{"fileName":"Brandon_Royval.json","fighterAnsiName":"Brandon Royval","mmaStatsName":null},{"fileName":"Brendan_Allen.json","fighterAnsiName":"Brendan Allen","mmaStatsName":null},{"fileName":"Brian_Kelleher.json","fighterAnsiName":"Brian Kelleher","mmaStatsName":null},{"fileName":"Brian_Ortega.json","fighterAnsiName":"Brian Ortega","mmaStatsName":null},{"fileName":"Bruno_Silva_(fighter).json","fighterAnsiName":"Bruno Silva","mmaStatsName":null},{"fileName":"Bryan_Barberena.json","fighterAnsiName":"Bryan Barberena","mmaStatsName":null},{"fileName":"Bryce_Mitchell.json","fighterAnsiName":"Bryce Mitchell","mmaStatsName":null},{"fileName":"Calvin_Kattar.json","fighterAnsiName":"Calvin Kattar","mmaStatsName":null},{"fileName":"Carla_Esparza.json","fighterAnsiName":"Carla Esparza","mmaStatsName":null},{"fileName":"Casey_O%27Neill.json","fighterAnsiName":"Casey O'Neill","mmaStatsName":null},{"fileName":"Charles_Jourdain.json","fighterAnsiName":"Charles Jourdain","mmaStatsName":null},{"fileName":"Charles_Oliveira.json","fighterAnsiName":"Charles Oliveira","mmaStatsName":null},{"fileName":"Chelsea_Chandler.json","fighterAnsiName":"Chelsea Chandler","mmaStatsName":null},{"fileName":"Chidi_Njokuani.json","fighterAnsiName":"Chidi Njokuani","mmaStatsName":null},{"fileName":"Choi_Doo-ho.json","fighterAnsiName":"Choi Doo-ho","mmaStatsName":null},{"fileName":"Chris_Curtis_(fighter).json","fighterAnsiName":"Chris Curtis","mmaStatsName":null},{"fileName":"Chris_Daukaus.json","fighterAnsiName":"Chris Daukaus","mmaStatsName":null},{"fileName":"Chris_Guti%C3%A9rrez.json","fighterAnsiName":"Chris Gutierrez","mmaStatsName":null},{"fileName":"Christos_Giagos.json","fighterAnsiName":"Christos Giagos","mmaStatsName":null},{"fileName":"Ciryl_Gane.json","fighterAnsiName":"Ciryl Gane","mmaStatsName":null},{"fileName":"Cody_Garbrandt.json","fighterAnsiName":"Cody Garbrandt","mmaStatsName":null},{"fileName":"Colby_Covington.json","fighterAnsiName":"Colby Covington","mmaStatsName":null},{"fileName":"Cory_Sandhagen.json","fighterAnsiName":"Cory Sandhagen","mmaStatsName":null},{"fileName":"Court_McGee.json","fighterAnsiName":"Court McGee","mmaStatsName":null},{"fileName":"Curtis_Blaydes.json","fighterAnsiName":"Curtis Blaydes","mmaStatsName":null},{"fileName":"Cynthia_Calvillo.json","fighterAnsiName":"Cynthia Calvillo","mmaStatsName":null},{"fileName":"Da_Un_Jung.json","fighterAnsiName":"Da Un Jung","mmaStatsName":null},{"fileName":"Damir_Ismagulov.json","fighterAnsiName":"Damir Ismagulov","mmaStatsName":null},{"fileName":"Damon_Jackson.json","fighterAnsiName":"Damon Jackson","mmaStatsName":null},{"fileName":"Dan_Hooker.json","fighterAnsiName":"Dan Hooker","mmaStatsName":null},{"fileName":"Dan_Ige.json","fighterAnsiName":"Dan Ige","mmaStatsName":null},{"fileName":"Daniel_Cormier.json","fighterAnsiName":"Daniel Cormier","mmaStatsName":null},{"fileName":"Daniel_Rodriguez_(fighter).json","fighterAnsiName":"Daniel Rodriguez","mmaStatsName":null},{"fileName":"Darren_Till.json","fighterAnsiName":"Darren Till","mmaStatsName":null},{"fileName":"David_Dvo%C5%99%C3%A1k.json","fighterAnsiName":"David Dvorak","mmaStatsName":null},{"fileName":"David_Teymur.json","fighterAnsiName":"David Teymur","mmaStatsName":null},{"fileName":"Deiveson_Figueiredo.json","fighterAnsiName":"Deiveson Figueiredo","mmaStatsName":null},{"fileName":"Derek_Brunson.json","fighterAnsiName":"Derek Brunson","mmaStatsName":null},{"fileName":"Deron_Winn.json","fighterAnsiName":"Deron Winn","mmaStatsName":null},{"fileName":"Derrick_Lewis.json","fighterAnsiName":"Derrick Lewis","mmaStatsName":null},{"fileName":"Devin_Clark_(fighter).json","fighterAnsiName":"Devin Clark","mmaStatsName":null},{"fileName":"Diego_Sanchez.json","fighterAnsiName":"Diego Sanchez","mmaStatsName":null},{"fileName":"Dominick_Cruz.json","fighterAnsiName":"Dominick Cruz","mmaStatsName":null},{"fileName":"Dominick_Reyes.json","fighterAnsiName":"Dominick Reyes","mmaStatsName":null},{"fileName":"Don%27Tale_Mayes.json","fighterAnsiName":"Don'Tale Mayes","mmaStatsName":null},{"fileName":"Drakkar_Klose.json","fighterAnsiName":"Drakkar Klose","mmaStatsName":null},{"fileName":"Drew_Dober.json","fighterAnsiName":"Drew Dober","mmaStatsName":null},{"fileName":"Dricus_du_Plessis.json","fighterAnsiName":"Dricus du Plessis","mmaStatsName":null},{"fileName":"Dustin_Poirier.json","fighterAnsiName":"Dustin Poirier","mmaStatsName":null},{"fileName":"Ed_Herman.json","fighterAnsiName":"Ed Herman","mmaStatsName":null},{"fileName":"Edmen_Shahbazyan.json","fighterAnsiName":"Edmen Shahbazyan","mmaStatsName":null},{"fileName":"Edson_Barboza.json","fighterAnsiName":"Edson Barboza","mmaStatsName":null},{"fileName":"Emily_Ducote.json","fighterAnsiName":"Emily Ducote","mmaStatsName":null},{"fileName":"Erin_Blanchfield.json","fighterAnsiName":"Erin Blanchfield","mmaStatsName":null},{"fileName":"Eryk_Anders.json","fighterAnsiName":"Eryk Anders","mmaStatsName":null},{"fileName":"Francis_Ngannou.json","fighterAnsiName":"Francis Ngannou","mmaStatsName":null},{"fileName":"Francisco_Trinaldo.json","fighterAnsiName":"Francisco Trinaldo","mmaStatsName":null},{"fileName":"Frankie_Edgar.json","fighterAnsiName":"Frankie Edgar","mmaStatsName":null},{"fileName":"Geoff_Neal.json","fighterAnsiName":"Geoff Neal","mmaStatsName":null},{"fileName":"Gerald_Meerschaert.json","fighterAnsiName":"Gerald Meerschaert","mmaStatsName":null},{"fileName":"Giga_Chikadze.json","fighterAnsiName":"Giga Chikadze","mmaStatsName":null},{"fileName":"Gilbert_Burns.json","fighterAnsiName":"Gilbert Burns","mmaStatsName":null},{"fileName":"Glover_Teixeira.json","fighterAnsiName":"Glover Teixeira","mmaStatsName":null},{"fileName":"Grant_Dawson.json","fighterAnsiName":"Grant Dawson","mmaStatsName":null},{"fileName":"Gregory_Rodrigues.json","fighterAnsiName":"Gregory Rodrigues","mmaStatsName":null},{"fileName":"Guido_Cannetti.json","fighterAnsiName":"Guido Cannetti","mmaStatsName":null},{"fileName":"Gunnar_Nelson_(fighter).json","fighterAnsiName":"Gunnar Nelson","mmaStatsName":null},{"fileName":"Hakeem_Dawodu.json","fighterAnsiName":"Hakeem Dawodu","mmaStatsName":null},{"fileName":"Hannah_Goldy.json","fighterAnsiName":"Hannah Goldy","mmaStatsName":null},{"fileName":"Henry_Cejudo.json","fighterAnsiName":"Henry Cejudo","mmaStatsName":null},{"fileName":"Holly_Holm.json","fighterAnsiName":"Holly Holm","mmaStatsName":null},{"fileName":"Ian_Garry.json","fighterAnsiName":"Ian Garry","mmaStatsName":null},{"fileName":"Ilia_Topuria.json","fighterAnsiName":"Ilia Topuria","mmaStatsName":null},{"fileName":"Ilir_Latifi.json","fighterAnsiName":"Ilir Latifi","mmaStatsName":null},{"fileName":"Ion_Cu%C8%9Belaba.json","fighterAnsiName":"Ion Cutelaba","mmaStatsName":null},{"fileName":"Irene_Aldana.json","fighterAnsiName":"Irene Aldana","mmaStatsName":null},{"fileName":"Islam_Makhachev.json","fighterAnsiName":"Islam Makhachev","mmaStatsName":null},{"fileName":"Israel_Adesanya.json","fighterAnsiName":"Israel Adesanya","mmaStatsName":null},{"fileName":"J%C3%A9ssica_Andrade.json","fighterAnsiName":"Jessica Andrade","mmaStatsName":null},{"fileName":"JJ_Aldrich.json","fighterAnsiName":"JJ Aldrich","mmaStatsName":null},{"fileName":"Jack_Hermansson.json","fighterAnsiName":"Jack Hermansson","mmaStatsName":null},{"fileName":"Jack_Shore.json","fighterAnsiName":"Jack Shore","mmaStatsName":null},{"fileName":"Jai_Herbert.json","fighterAnsiName":"Jai Herbert","mmaStatsName":null},{"fileName":"Jailton_Almeida.json","fighterAnsiName":"Jailton Almeida","mmaStatsName":null},{"fileName":"Jairzinho_Rozenstruik.json","fighterAnsiName":"Jairzinho Rozenstruik","mmaStatsName":null},{"fileName":"Jake_Matthews_(fighter).json","fighterAnsiName":"Jake Matthews","mmaStatsName":null},{"fileName":"Jalin_Turner.json","fighterAnsiName":"Jalin Turner","mmaStatsName":null},{"fileName":"Jamahal_Hill.json","fighterAnsiName":"Jamahal Hill","mmaStatsName":null},{"fileName":"Jamie_Pickett.json","fighterAnsiName":"Jamie Pickett","mmaStatsName":null},{"fileName":"Jan_B%C5%82achowicz.json","fighterAnsiName":"Jan Blachowicz","mmaStatsName":null},{"fileName":"Jared_Cannonier.json","fighterAnsiName":"Jared Cannonier","mmaStatsName":null},{"fileName":"Jared_Gordon.json","fighterAnsiName":"Jared Gordon","mmaStatsName":null},{"fileName":"Jeff_Molina.json","fighterAnsiName":"Jeff Molina","mmaStatsName":null},{"fileName":"Jennifer_Maia.json","fighterAnsiName":"Jennifer Maia","mmaStatsName":null},{"fileName":"Jesse_Ronson.json","fighterAnsiName":"Jesse Ronson","mmaStatsName":null},{"fileName":"Jessica_Penne.json","fighterAnsiName":"Jessica Penne","mmaStatsName":null},{"fileName":"Ji%C5%99%C3%AD_Proch%C3%A1zka.json","fighterAnsiName":"Jiri Prochazka","mmaStatsName":null},{"fileName":"Jim_Miller_(fighter).json","fighterAnsiName":"Jim Miller","mmaStatsName":null},{"fileName":"Jimmy_Crute.json","fighterAnsiName":"Jimmy Crute","mmaStatsName":null},{"fileName":"Joaquim_Silva_(fighter).json","fighterAnsiName":"Joaquim Silva","mmaStatsName":null},{"fileName":"Joaquin_Buckley.json","fighterAnsiName":"Joaquin Buckley","mmaStatsName":null},{"fileName":"John_Makdessi.json","fighterAnsiName":"John Makdessi","mmaStatsName":null},{"fileName":"Johnny_Walker_(fighter).json","fighterAnsiName":"Johnny Walker","mmaStatsName":null},{"fileName":"Jon_Jones.json","fighterAnsiName":"Jon Jones","mmaStatsName":null},{"fileName":"Jonathan_Martinez.json","fighterAnsiName":"Jonathan Martinez","mmaStatsName":null},{"fileName":"Jonathan_Pearce_(fighter).json","fighterAnsiName":"Jonathan Pearce","mmaStatsName":null},{"fileName":"Jordan_Leavitt.json","fighterAnsiName":"Jordan Leavitt","mmaStatsName":null},{"fileName":"Jorge_Masvidal.json","fighterAnsiName":"Jorge Masvidal","mmaStatsName":null},{"fileName":"Jos%C3%A9_Aldo.json","fighterAnsiName":"Jose Aldo","mmaStatsName":null},{"fileName":"Jose패_Aldo.json","fighterAnsiName":"Jose패 Aldo","mmaStatsName":null},{"fileName":"Josh_Emmett.json","fighterAnsiName":"Josh Emmett","mmaStatsName":null},{"fileName":"Journey_Newson.json","fighterAnsiName":"Journey Newson","mmaStatsName":null},{"fileName":"Julia_Avila.json","fighterAnsiName":"Julia Avila","mmaStatsName":null},{"fileName":"Julian_Erosa.json","fighterAnsiName":"Julian Erosa","mmaStatsName":null},{"fileName":"Julian_Marquez.json","fighterAnsiName":"Julian Marquez","mmaStatsName":null},{"fileName":"Julianna_Pe%C3%B1a.json","fighterAnsiName":"Julianna Pena","mmaStatsName":null},{"fileName":"Julio_Arce.json","fighterAnsiName":"Julio Arce","mmaStatsName":null},{"fileName":"Junior_dos_Santos.json","fighterAnsiName":"Junior dos Santos","mmaStatsName":null},{"fileName":"Justin_Gaethje.json","fighterAnsiName":"Justin Gaethje","mmaStatsName":null},{"fileName":"Justin_Tafa.json","fighterAnsiName":"Justin Tafa","mmaStatsName":null},{"fileName":"Kai_Kara-France.json","fighterAnsiName":"Kai Kara-France","mmaStatsName":null},{"fileName":"Kamaru_Usman.json","fighterAnsiName":"Kamaru Usman","mmaStatsName":null},{"fileName":"Karol_Rosa.json","fighterAnsiName":"Karol Rosa","mmaStatsName":null},{"fileName":"Karolina_Kowalkiewicz.json","fighterAnsiName":"Karolina Kowalkiewicz","mmaStatsName":null},{"fileName":"Katlyn_Chookagian.json","fighterAnsiName":"Katlyn Chookagian","mmaStatsName":null},{"fileName":"Kelvin_Gastelum.json","fighterAnsiName":"Kelvin Gastelum","mmaStatsName":null},{"fileName":"Kennedy_Nzechukwu.json","fighterAnsiName":"Kennedy Nzechukwu","mmaStatsName":null},{"fileName":"Ketlen_Vieira.json","fighterAnsiName":"Ketlen Vieira","mmaStatsName":null},{"fileName":"Kevin_Holland.json","fighterAnsiName":"Kevin Holland","mmaStatsName":null},{"fileName":"Kevin_Lee.json","fighterAnsiName":"Kevin Lee","mmaStatsName":null},{"fileName":"Khabib_Nurmagomedov.json","fighterAnsiName":"Khabib Nurmagomedov","mmaStatsName":null},{"fileName":"Khalil_Rountree_Jr..json","fighterAnsiName":"Khalil Rountree Jr.","mmaStatsName":null},{"fileName":"Khamzat_Chimaev.json","fighterAnsiName":"Khamzat Chimaev","mmaStatsName":null},{"fileName":"Krzysztof_Jotko.json","fighterAnsiName":"Krzysztof Jotko","mmaStatsName":null},{"fileName":"Kyle_Daukaus.json","fighterAnsiName":"Kyle Daukaus","mmaStatsName":null},{"fileName":"Kyle_Nelson_(fighter).json","fighterAnsiName":"Kyle Nelson","mmaStatsName":null},{"fileName":"Lauren_Murphy.json","fighterAnsiName":"Lauren Murphy","mmaStatsName":null},{"fileName":"Leon_Edwards.json","fighterAnsiName":"Leon Edwards","mmaStatsName":null},{"fileName":"Leonardo_Santos_(fighter).json","fighterAnsiName":"Leonardo Santos","mmaStatsName":null},{"fileName":"Lerone_Murphy.json","fighterAnsiName":"Lerone Murphy","mmaStatsName":null},{"fileName":"Li_Jingliang.json","fighterAnsiName":"Li Jingliang","mmaStatsName":null},{"fileName":"Lina_L%C3%A4nsberg.json","fighterAnsiName":"Lina Lansberg","mmaStatsName":null},{"fileName":"Lucie_Pudilov%C3%A1.json","fighterAnsiName":"Lucie Pudilova","mmaStatsName":null},{"fileName":"Luke_Rockhold.json","fighterAnsiName":"Luke Rockhold","mmaStatsName":null},{"fileName":"Lupita_Godinez.json","fighterAnsiName":"Lupita Godinez","mmaStatsName":null},{"fileName":"Lyoto_Machida.json","fighterAnsiName":"Lyoto Machida","mmaStatsName":null},{"fileName":"Mackenzie_Dern.json","fighterAnsiName":"Mackenzie Dern","mmaStatsName":null},{"fileName":"Macy_Chiasson.json","fighterAnsiName":"Macy Chiasson","mmaStatsName":null},{"fileName":"Magomed_Ankalaev.json","fighterAnsiName":"Magomed Ankalaev","mmaStatsName":null},{"fileName":"Makwan_Amirkhani.json","fighterAnsiName":"Makwan Amirkhani","mmaStatsName":null},{"fileName":"Manel_Kape.json","fighterAnsiName":"Manel Kape","mmaStatsName":null},{"fileName":"Manon_Fiorot.json","fighterAnsiName":"Manon Fiorot","mmaStatsName":null},{"fileName":"Marc-Andr%C3%A9_Barriault.json","fighterAnsiName":"Marc-Andre Barriault","mmaStatsName":null},{"fileName":"Marcin_Prachnio.json","fighterAnsiName":"Marcin Prachnio","mmaStatsName":null},{"fileName":"Marcin_Tybura.json","fighterAnsiName":"Marcin Tybura","mmaStatsName":null},{"fileName":"Marina_Rodriguez.json","fighterAnsiName":"Marina Rodriguez","mmaStatsName":null},{"fileName":"Mario_Bautista.json","fighterAnsiName":"Mario Bautista","mmaStatsName":null},{"fileName":"Marlon_Moraes.json","fighterAnsiName":"Marlon Moraes","mmaStatsName":null},{"fileName":"Marlon_Vera.json","fighterAnsiName":"Marlon Vera","mmaStatsName":null},{"fileName":"Marvin_Vettori.json","fighterAnsiName":"Marvin Vettori","mmaStatsName":null},{"fileName":"Maryna_Moroz.json","fighterAnsiName":"Maryna Moroz","mmaStatsName":null},{"fileName":"Mateusz_Gamrot.json","fighterAnsiName":"Mateusz Gamrot","mmaStatsName":null},{"fileName":"Matheus_Nicolau.json","fighterAnsiName":"Matheus Nicolau","mmaStatsName":null},{"fileName":"Matt_Brown_(fighter).json","fighterAnsiName":"Matt Brown","mmaStatsName":null},{"fileName":"Matt_Schnell.json","fighterAnsiName":"Matt Schnell","mmaStatsName":null},{"fileName":"Matthew_Semelsberger.json","fighterAnsiName":"Matthew Semelsberger","mmaStatsName":null},{"fileName":"Mauri패cio_Rua.json","fighterAnsiName":"Mauri패cio Rua","mmaStatsName":null},{"fileName":"Max_Holloway.json","fighterAnsiName":"Max Holloway","mmaStatsName":null},{"fileName":"Maycee_Barber.json","fighterAnsiName":"Maycee Barber","mmaStatsName":null},{"fileName":"Mayra_Bueno_Silva.json","fighterAnsiName":"Mayra Bueno Silva","mmaStatsName":null},{"fileName":"Merab_Dvalishvili.json","fighterAnsiName":"Merab Dvalishvili","mmaStatsName":null},{"fileName":"Micha%C5%82_Oleksiejczuk.json","fighterAnsiName":"Michal Oleksiejczuk","mmaStatsName":null},{"fileName":"Michael_Chandler.json","fighterAnsiName":"Michael Chandler","mmaStatsName":null},{"fileName":"Michael_Chiesa.json","fighterAnsiName":"Michael Chiesa","mmaStatsName":null},{"fileName":"Michel_Pereira.json","fighterAnsiName":"Michel Pereira","mmaStatsName":null},{"fileName":"Michelle_Waterson.json","fighterAnsiName":"Michelle Waterson","mmaStatsName":null},{"fileName":"Miesha_Tate.json","fighterAnsiName":"Miesha Tate","mmaStatsName":null},{"fileName":"Miles_Johns.json","fighterAnsiName":"Miles Johns","mmaStatsName":null},{"fileName":"Misha_Cirkunov.json","fighterAnsiName":"Misha Cirkunov","mmaStatsName":null},{"fileName":"Molly_McCann.json","fighterAnsiName":"Molly McCann","mmaStatsName":null},{"fileName":"Montana_De_La_Rosa.json","fighterAnsiName":"Montana De La Rosa","mmaStatsName":null},{"fileName":"Movsar_Evloev.json","fighterAnsiName":"Movsar Evloev","mmaStatsName":null},{"fileName":"Muhammad_Mokaev.json","fighterAnsiName":"Muhammad Mokaev","mmaStatsName":null},{"fileName":"Muslim_Salikhov.json","fighterAnsiName":"Muslim Salikhov","mmaStatsName":null},{"fileName":"Nasrat_Haqparast.json","fighterAnsiName":"Nasrat Haqparast","mmaStatsName":null},{"fileName":"Nassourdine_Imavov.json","fighterAnsiName":"Nassourdine Imavov","mmaStatsName":null},{"fileName":"Nate_Diaz.json","fighterAnsiName":"Nate Diaz","mmaStatsName":null},{"fileName":"Nate_Landwehr.json","fighterAnsiName":"Nate Landwehr","mmaStatsName":null},{"fileName":"Nathaniel_Wood_(fighter).json","fighterAnsiName":"Nathaniel Wood","mmaStatsName":null},{"fileName":"Neil_Magny.json","fighterAnsiName":"Neil Magny","mmaStatsName":null},{"fileName":"Nik_Lentz.json","fighterAnsiName":"Nik Lentz","mmaStatsName":null},{"fileName":"Nikita_Krylov.json","fighterAnsiName":"Nikita Krylov","mmaStatsName":null},{"fileName":"Niko_Price.json","fighterAnsiName":"Niko Price","mmaStatsName":null},{"fileName":"Nina_Nunes.json","fighterAnsiName":"Nina Nunes","mmaStatsName":null},{"fileName":"Norma_Dumont.json","fighterAnsiName":"Norma Dumont","mmaStatsName":null},{"fileName":"Ode%27_Osbourne.json","fighterAnsiName":"Ode' Osbourne","mmaStatsName":null},{"fileName":"Ovince_Saint_Preux.json","fighterAnsiName":"Ovince Saint Preux","mmaStatsName":null},{"fileName":"Paddy_Pimblett.json","fighterAnsiName":"Paddy Pimblett","mmaStatsName":null},{"fileName":"Pannie_Kianzad.json","fighterAnsiName":"Pannie Kianzad","mmaStatsName":null},{"fileName":"Paul_Craig.json","fighterAnsiName":"Paul Craig","mmaStatsName":null},{"fileName":"Paulo_Costa.json","fighterAnsiName":"Paulo Costa","mmaStatsName":null},{"fileName":"Pedro_Munhoz.json","fighterAnsiName":"Pedro Munhoz","mmaStatsName":null},{"fileName":"Petr_Yan.json","fighterAnsiName":"Petr Yan","mmaStatsName":null},{"fileName":"Philip_Rowe.json","fighterAnsiName":"Philip Rowe","mmaStatsName":null},{"fileName":"Philipe_Lins.json","fighterAnsiName":"Philipe Lins","mmaStatsName":null},{"fileName":"Polyana_Viana.json","fighterAnsiName":"Polyana Viana","mmaStatsName":null},{"fileName":"Priscila_Cachoeira.json","fighterAnsiName":"Priscila Cachoeira","mmaStatsName":null},{"fileName":"Rafael_Fiziev.json","fighterAnsiName":"Rafael Fiziev","mmaStatsName":null},{"fileName":"Rafael_dos_Anjos.json","fighterAnsiName":"Rafael dos Anjos","mmaStatsName":null},{"fileName":"Randy_Brown_(fighter).json","fighterAnsiName":"Randy Brown","mmaStatsName":null},{"fileName":"Rani_Yahya.json","fighterAnsiName":"Rani Yahya","mmaStatsName":null},{"fileName":"Raoni_Barcelos.json","fighterAnsiName":"Raoni Barcelos","mmaStatsName":null},{"fileName":"Raquel_Pennington.json","fighterAnsiName":"Raquel Pennington","mmaStatsName":null},{"fileName":"Renato_Moicano.json","fighterAnsiName":"Renato Moicano","mmaStatsName":null},{"fileName":"Ricardo_Ramos_(fighter).json","fighterAnsiName":"Ricardo Ramos","mmaStatsName":null},{"fileName":"Ricky_Sim%C3%B3n.json","fighterAnsiName":"Ricky Simon","mmaStatsName":null},{"fileName":"Rob_Font.json","fighterAnsiName":"Rob Font","mmaStatsName":null},{"fileName":"Robbie_Lawler.json","fighterAnsiName":"Robbie Lawler","mmaStatsName":null},{"fileName":"Robert_Whittaker_(fighter).json","fighterAnsiName":"Robert Whittaker","mmaStatsName":null},{"fileName":"Rodrigo_Nascimento.json","fighterAnsiName":"Rodrigo Nascimento","mmaStatsName":null},{"fileName":"Roman_Dolidze.json","fighterAnsiName":"Roman Dolidze","mmaStatsName":null},{"fileName":"Rose_Namajunas.json","fighterAnsiName":"Rose Namajunas","mmaStatsName":null},{"fileName":"Ryan_Spann.json","fighterAnsiName":"Ryan Spann","mmaStatsName":null},{"fileName":"Said_Nurmagomedov.json","fighterAnsiName":"Said Nurmagomedov","mmaStatsName":null},{"fileName":"Sam_Alvey.json","fighterAnsiName":"Sam Alvey","mmaStatsName":null},{"fileName":"Santiago_Ponzinibbio.json","fighterAnsiName":"Santiago Ponzinibbio","mmaStatsName":null},{"fileName":"Sara_McMann.json","fighterAnsiName":"Sara McMann","mmaStatsName":null},{"fileName":"Sean_Brady_(fighter).json","fighterAnsiName":"Sean Brady","mmaStatsName":null},{"fileName":"Sean_O%27Malley_(fighter).json","fighterAnsiName":"Sean O'Malley","mmaStatsName":null},{"fileName":"Sean_Strickland.json","fighterAnsiName":"Sean Strickland","mmaStatsName":null},{"fileName":"Sergei_Pavlovich.json","fighterAnsiName":"Sergei Pavlovich","mmaStatsName":null},{"fileName":"Sergey_Morozov_(fighter).json","fighterAnsiName":"Sergey Morozov","mmaStatsName":null},{"fileName":"Sergey_Spivak.json","fighterAnsiName":"Sergey Spivak","mmaStatsName":null},{"fileName":"Shamil_Abdurakhimov.json","fighterAnsiName":"Shamil Abdurakhimov","mmaStatsName":null},{"fileName":"Shamil_Gamzatov.json","fighterAnsiName":"Shamil Gamzatov","mmaStatsName":null},{"fileName":"Shavkat_Rakhmonov.json","fighterAnsiName":"Shavkat Rakhmonov","mmaStatsName":null},{"fileName":"Sijara_Eubanks.json","fighterAnsiName":"Sijara Eubanks","mmaStatsName":null},{"fileName":"Sodiq_Yusuff.json","fighterAnsiName":"Sodiq Yusuff","mmaStatsName":null},{"fileName":"Song_Kenan.json","fighterAnsiName":"Song Kenan","mmaStatsName":null},{"fileName":"Song_Yadong.json","fighterAnsiName":"Song Yadong","mmaStatsName":null},{"fileName":"Stephanie_Egger.json","fighterAnsiName":"Stephanie Egger","mmaStatsName":null},{"fileName":"Stephen_Thompson_(fighter).json","fighterAnsiName":"Stephen Thompson","mmaStatsName":null},{"fileName":"Stipe_Miocic.json","fighterAnsiName":"Stipe Miocic","mmaStatsName":null},{"fileName":"Su_Mudaerji.json","fighterAnsiName":"Su Mudaerji","mmaStatsName":null},{"fileName":"T.J._Dillashaw.json","fighterAnsiName":"T.J. Dillashaw","mmaStatsName":null},{"fileName":"Tabatha_Ricci.json","fighterAnsiName":"Tabatha Ricci","mmaStatsName":null},{"fileName":"Tagir_Ulanbekov.json","fighterAnsiName":"Tagir Ulanbekov","mmaStatsName":null},{"fileName":"Tai_Tuivasa.json","fighterAnsiName":"Tai Tuivasa","mmaStatsName":null},{"fileName":"Taila_Santos.json","fighterAnsiName":"Taila Santos","mmaStatsName":null},{"fileName":"Tanner_Boser.json","fighterAnsiName":"Tanner Boser","mmaStatsName":null},{"fileName":"Tecia_Torres.json","fighterAnsiName":"Tecia Torres","mmaStatsName":null},{"fileName":"The_Korean_Zombie.json","fighterAnsiName":"The Korean Zombie","mmaStatsName":null},{"fileName":"Thiago_Santos_(fighter).json","fighterAnsiName":"Thiago Santos","mmaStatsName":null},{"fileName":"Tim_Elliott.json","fighterAnsiName":"Tim Elliott","mmaStatsName":null},{"fileName":"Tom_Aspinall.json","fighterAnsiName":"Tom Aspinall","mmaStatsName":null},{"fileName":"Tony_Ferguson.json","fighterAnsiName":"Tony Ferguson","mmaStatsName":null},{"fileName":"Tracy_Cortez.json","fighterAnsiName":"Tracy Cortez","mmaStatsName":null},{"fileName":"Trevin_Jones.json","fighterAnsiName":"Trevin Jones","mmaStatsName":null},{"fileName":"Tyson_Nam.json","fighterAnsiName":"Tyson Nam","mmaStatsName":null},{"fileName":"Tyson_Pedro.json","fighterAnsiName":"Tyson Pedro","mmaStatsName":null},{"fileName":"Umar_Nurmagomedov.json","fighterAnsiName":"Umar Nurmagomedov","mmaStatsName":null},{"fileName":"Valentina_Shevchenko.json","fighterAnsiName":"Valentina Shevchenko","mmaStatsName":null},{"fileName":"Vanessa_Demopoulos.json","fighterAnsiName":"Vanessa Demopoulos","mmaStatsName":null},{"fileName":"Vicente_Luque.json","fighterAnsiName":"Vicente Luque","mmaStatsName":null},{"fileName":"Vince_Morales.json","fighterAnsiName":"Vince Morales","mmaStatsName":null},{"fileName":"Virna_Jandiroba.json","fighterAnsiName":"Virna Jandiroba","mmaStatsName":null},{"fileName":"Vitor_Belfort.json","fighterAnsiName":"Vitor Belfort","mmaStatsName":null},{"fileName":"Viviane_Ara%C3%BAjo_(fighter).json","fighterAnsiName":"Viviane Araujo","mmaStatsName":null},{"fileName":"Volkan_Oezdemir.json","fighterAnsiName":"Volkan Oezdemir","mmaStatsName":null},{"fileName":"William_Knight_(fighter).json","fighterAnsiName":"William Knight","mmaStatsName":null},{"fileName":"Wu_Yanan_(fighter).json","fighterAnsiName":"Wu Yanan","mmaStatsName":null},{"fileName":"Yair_Rodr%C3%ADguez.json","fighterAnsiName":"Yair Rodriguez","mmaStatsName":null},{"fileName":"Yan_Xiaonan.json","fighterAnsiName":"Yan Xiaonan","mmaStatsName":null},{"fileName":"Yana_Kunitskaya.json","fighterAnsiName":"Yana Kunitskaya","mmaStatsName":null},{"fileName":"Zhang_Weili.json","fighterAnsiName":"Zhang Weili","mmaStatsName":null}]