[
    {
        "date": "Sep 14, 2024",
        "eventName": "UFC 306: O'Malley vs. Dvalishvili",
        "url": "/wiki/UFC_306"
    },
    {
        "date": "Sep 7, 2024",
        "eventName": "UFC Fight Night: Burns vs. Brady",
        "url": "/wiki/UFC_Fight_Night:_Burns_vs._Brady"
    },
    {
        "date": "Aug 24, 2024",
        "eventName": "UFC on ESPN: Cannonier vs. Borralho",
        "url": "/wiki/UFC_on_ESPN:_Cannonier_vs._Borralho"
    },
    {
        "date": "Aug 18, 2024",
        "eventName": "UFC 305: du Plessis vs. Adesanya",
        "url": "/wiki/UFC_305"
    },
    {
        "date": "Aug 10, 2024",
        "eventName": "UFC on ESPN: Tybura vs. Spivac 2",
        "url": "/wiki/UFC_on_ESPN:_Tybura_vs._Spivac_2"
    },
    {
        "date": "Aug 3, 2024",
        "eventName": "UFC on ABC: Sandhagen vs. Nurmagomedov",
        "url": "/wiki/UFC_on_ABC:_Sandhagen_vs._Nurmagomedov"
    }
]