{"fighterInfo":{"wikiUrl":"https://en.wikipedia.org//wiki/Bruno_Gustavo_da_Silva","name":"Bruno Silva","ageFullString":" (1990-03-16) 16 March 1990 (age&#160;33)","age":"33","birthplace":"Piracicaba, Brazil","nickname":"Bulldog","height":"5 ft 4 in (1.63 m)","weight":"125.5 lb (57 kg; 9 st 0 lb)","division":"BantamweightFlyweight","reach":"65 in (165 cm)","teams":["Black House (2012–2015)","Fight Ready MMA (2015–present)"],"team":"Fight Ready MMA (2015–present)","rank":"Black belt in Brazilian jiu-jitsu","yearsActive":"2011–present","totalFights":"21","wins":"13","knockoutWins":"1","submissionWins":"1","decisionWins":"3","losses":"5","draws":"2","nocontests":"1","relevantImages":false},"record":[{"result":"Win","record":"13–5–2 (1)","opponentName":"Tyson Nam","method":"Technical Submission (rear-naked choke)","event":"UFC Fight Night: Yan vs. Dvalishvili","date":"March 11, 2023","round":"2","time":"1:23","location":"Las Vegas, Nevada, United States","notes":"Performance of the Night.","year":"2023","opponentInfoAtTheTime":{"fighter":{"rank":" 15","link":"https://mma-stats.com/fighters/Tyson-Nam","name":"Tyson Nam"},"division":" Flyweight ","date":"February 14, 2023","formattedDate":"2023-02"},"fighterRankAtTheTime":0},{"result":"Win","record":"12–5–2 (1)","opponentName":"Victor Rodriguez","method":"KO (punches)","event":"UFC Fight Night: Font vs. Garbrandt","date":"May 22, 2021","round":"1","time":"1:00","location":"Las Vegas, Nevada, United States","notes":"Performance of the Night.","year":"2021","opponentInfoAtTheTime":0,"fighterRankAtTheTime":0},{"result":"Win","record":"11–5–2 (1)","opponentName":"JP Buys","method":"TKO (punches)","event":"UFC on ESPN: Brunson vs. Holland","date":"March 20, 2021","round":"2","time":"2:56","location":"Las Vegas, Nevada, United States","notes":"Performance of the Night.","year":"2021","opponentInfoAtTheTime":0,"fighterRankAtTheTime":0},{"result":"Loss","record":"10–5–2 (1)","opponentName":"Tagir Ulanbekov","method":"Decision (unanimous)","event":"UFC Fight Night: Moraes vs. Sandhagen","date":"October 11, 2020","round":"3","time":"5:00","location":"Abu Dhabi, United Arab Emirates","notes":"","year":"2020","opponentInfoAtTheTime":{"fighter":{"rank":" 15","link":"https://mma-stats.com/fighters/Tagir-Ulanbekov","name":"Tagir Ulanbekov"},"division":" Flyweight ","date":"October 11, 2021","formattedDate":"2021-10","wasInTheFuture":true},"fighterRankAtTheTime":0},{"result":"Loss","record":"10–4–2 (1)","opponentName":"David Dvořák","method":"Decision (unanimous)","event":"UFC Fight Night: Lee vs. Oliveira","date":"March 14, 2020","round":"3","time":"5:00","location":"Brasília, Brazil","notes":"Return to Flyweight.","year":"2020","opponentInfoAtTheTime":{"fighter":{"name":"David Dvořák","rank":"10","link":"/wiki/David_Dvo%C5%99%C3%A1k"},"division":"Flyweight","date":"May 16, 2023","formattedDate":"2023-05","wasInTheFuture":true},"fighterRankAtTheTime":0},{"result":"NC","record":"10–3–2 (1)","opponentName":"Khalid Taha","method":"NC (overturned)","event":"UFC 243","date":"October 6, 2019","round":"3","time":"3:00","location":"Melbourne, Australia","notes":"Catchweight (137 lb) bout; Taha missed weight. Originally a submission (arm-triangle choke) win for Taha; overturned after he tested positive for furosemide.","year":"2019","opponentInfoAtTheTime":0,"fighterRankAtTheTime":0},{"result":"Win","record":"10–3–2","opponentName":"Ralph Acosta","method":"Decision (unanimous)","event":"World Fighting Federation 40","date":"December 15, 2018","round":"3","time":"5:00","location":"Chandler, Arizona, United States","notes":"Won the WFF Flyweight Championship.","year":"2018","opponentInfoAtTheTime":0,"fighterRankAtTheTime":0},{"result":"Win","record":"9–3–2","opponentName":"Joe Madrid","method":"TKO (punches)","event":"World Fighting Federation 35","date":"August 19, 2017","round":"1","time":"4:23","location":"Chandler, Arizona, United States","notes":"","year":"2017","opponentInfoAtTheTime":0,"fighterRankAtTheTime":0},{"result":"Draw","record":"8–3–2","opponentName":"Casey Kenney","method":"Draw (split)","event":"LFA 11","date":"May 5, 2017","round":"3","time":"5:00","location":"Phoenix, Arizona, United States","notes":"Flyweight bout.","year":"2017","opponentInfoAtTheTime":{"fighter":{"rank":"15","link":"https://mma-stats.com/fighters/Casey--Kenney","name":"Casey Kenney"},"division":"Bantamweight","date":"October 28, 2019","formattedDate":"2019-10","wasInTheFuture":true},"fighterRankAtTheTime":0},{"result":"Loss","record":"8–3–1","opponentName":"Adalto Prado","method":"KO (head kick)","event":"Aspera FC 44","date":"September 10, 2016","round":"1","time":"0:07","location":"São Pedro, São Paulo, Brazil","notes":"Bantamweight debut.","year":"2016","opponentInfoAtTheTime":0,"fighterRankAtTheTime":0},{"result":"Win","record":"8–2–1","opponentName":"Matt Betzold","method":"Decision (split)","event":"World Fighting Federation 25","date":"November 7, 2015","round":"3","time":"5:00","location":"Chandler, Arizona, United States","notes":"","year":"2015","opponentInfoAtTheTime":0,"fighterRankAtTheTime":0},{"result":"Win","record":"7–2–1","opponentName":"Heider Prais","method":"Submission (rear-naked choke)","event":"Team Nogueira: MMA Fight Live","date":"September 4, 2014","round":"3","time":"3:23","location":"Rio de Janeiro, Brazil","notes":"","year":"2014","opponentInfoAtTheTime":0,"fighterRankAtTheTime":0},{"result":"Win","record":"6–2–1","opponentName":"Soslenis Silva","method":"Submission (rear-naked choke)","event":"Talent MMA Circuit 8","date":"April 12, 2014","round":"3","time":"4:33","location":"Valinhos, Brazil","notes":"","year":"2014","opponentInfoAtTheTime":0,"fighterRankAtTheTime":0},{"result":"Win","record":"5–2–1","opponentName":"Júlio Cesar Moraes","method":"KO (spinning wheel kick)","event":"Team Nogueira: MMA Circuit 4","date":"November 5, 2013","round":"3","time":"0:00","location":"Rio de Janeiro, Brazil","notes":"","year":"2013","opponentInfoAtTheTime":0,"fighterRankAtTheTime":0},{"result":"Win","record":"4–2–1","opponentName":"Atila Oliveira","method":"Decision (unanimous)","event":"MMA Challenge: Ponte Preta","date":"September 20, 2012","round":"3","time":"5:00","location":"Campinas, Brazil","notes":"","year":"2012","opponentInfoAtTheTime":0,"fighterRankAtTheTime":0},{"result":"Draw","record":"3–2–1","opponentName":"Yury Valenzuela","method":"Draw (majority)","event":"Encontro Fight 2","date":"July 27, 2012","round":"3","time":"5:00","location":"Santa Bárbara d'Oeste, Brazil","notes":"","year":"2012","opponentInfoAtTheTime":0,"fighterRankAtTheTime":0},{"result":"Loss","record":"3–2","opponentName":"Wesley Batista","method":"Decision (unanimous)","event":"Corumbatai Fight","date":"July 14, 2012","round":"3","time":"5:00","location":"Corumbataí, Brazil","notes":"","year":"2012","opponentInfoAtTheTime":0,"fighterRankAtTheTime":0},{"result":"Win","record":"3–1","opponentName":"James Carvalho","method":"TKO (doctor stoppage)","event":"Arena Fight Uberlandia 4","date":"December 10, 2011","round":"1","time":"5:00","location":"Uberlândia, Brazil","notes":"","year":"2011","opponentInfoAtTheTime":0,"fighterRankAtTheTime":0},{"result":"Loss","record":"2–1","opponentName":"Rodrigo Marcos","method":"Submission (armbar)","event":"Hombres de Honor 29","date":"September 24, 2011","round":"3","time":"0:22","location":"Sorocaba, Brazil","notes":"","year":"2011","opponentInfoAtTheTime":0,"fighterRankAtTheTime":0},{"result":"Win","record":"2–0","opponentName":"Renato Higen Carriel","method":"Decision (unanimous)","event":"Circuito MMA Kyokushinkaikan 2","date":"June 4, 2011","round":"3","time":"5:00","location":"Sorocaba, Brazil","notes":"","year":"2011","opponentInfoAtTheTime":0,"fighterRankAtTheTime":0},{"result":"Win","record":"1–0","opponentName":"Paulo Magueta","method":"Submission","event":"Circuito MMA Kyokushinkaikan","date":"February 6, 2011","round":"1","time":"1:31","location":"Sorocaba, Brazil","notes":"","year":"2011","opponentInfoAtTheTime":0,"fighterRankAtTheTime":0}],"recordString":""}