{"fighterInfo":{"wikiUrl":"https://en.wikipedia.org//wiki/Ian_Machado_Garry","name":"Ian Machado Garry","ageFullString":" (1997-11-17) 17 November 1997 (age&#160;25)","age":"25","birthplace":"Portmarnock, Ireland","nickname":"The Future","height":"6 ft 3 in (1.91 m)","weight":"170 lb (77 kg; 12 st 2 lb)","division":"Welterweight","reach":"74.0 in (188 cm)","style":"Boxing, Judo","fightingOutOf":"Ireland","teams":["Kill Cliff FC"],"team":"Kill Cliff FC","rank":"Black belt in Judo","yearsActive":"2019–present","totalFights":"7","wins":"6","knockoutWins":"5","submissionWins":"1","decisionWins":"1","losses":"1","relevantImages":false},"record":[{"result":"Win","record":"12–0","opponentName":"Daniel Rodriguez","method":"TKO (head kick and punches)","event":"UFC on ABC: Rozenstruik vs. Almeida","date":"May 13, 2023","round":"1","time":"2:57","location":"Charlotte, North Carolina, United States","notes":"Performance of the Night.","year":"2023","opponentInfoAtTheTime":{"fighter":{"rank":" 15","link":"https://mma-stats.com/fighters/Daniel-Rodriguez","name":"Daniel Rodriguez"},"division":" Welterweight ","date":"November 21, 2022","formattedDate":"2022-11"},"fighterRankAtTheTime":{"fighter":{"name":"Ian Machado Garry","rank":"13","link":"/wiki/Ian_Machado_Garry"},"division":"Welterweight","date":"May 16, 2023","formattedDate":"2023-05"}},{"result":"Win","record":"11–0","opponentName":"Song Kenan","method":"TKO (punches)","event":"UFC 285","date":"March 4, 2023","round":"3","time":"4:22","location":"Las Vegas, Nevada, United States","notes":"","year":"2023","opponentInfoAtTheTime":0,"fighterRankAtTheTime":{"fighter":{"name":"Ian Machado Garry","rank":"13","link":"/wiki/Ian_Machado_Garry"},"division":"Welterweight","date":"May 16, 2023","formattedDate":"2023-05"}},{"result":"Win","record":"10–0","opponentName":"Gabriel Green","method":"Decision (unanimous)","event":"UFC 276","date":"July 2, 2022","round":"3","time":"5:00","location":"Las Vegas, Nevada, United States","notes":"","year":"2022","opponentInfoAtTheTime":0,"fighterRankAtTheTime":{"fighter":{"name":"Ian Machado Garry","rank":"13","link":"/wiki/Ian_Machado_Garry"},"division":"Welterweight","date":"May 16, 2023","formattedDate":"2023-05"}},{"result":"Win","record":"9–0","opponentName":"Darian Weeks","method":"Decision (unanimous)","event":"UFC 273","date":"April 9, 2022","round":"3","time":"5:00","location":"Jacksonville, Florida, United States","notes":"","year":"2022","opponentInfoAtTheTime":0,"fighterRankAtTheTime":{"fighter":{"name":"Ian Machado Garry","rank":"13","link":"/wiki/Ian_Machado_Garry"},"division":"Welterweight","date":"May 16, 2023","formattedDate":"2023-05","wasInTheFuture":true}},{"result":"Win","record":"8–0","opponentName":"Jordan Williams","method":"KO (punches)","event":"UFC 268","date":"November 6, 2021","round":"1","time":"4:59","location":"New York City, New York, United States","notes":"","year":"2021","opponentInfoAtTheTime":0,"fighterRankAtTheTime":{"fighter":{"name":"Ian Machado Garry","rank":"13","link":"/wiki/Ian_Machado_Garry"},"division":"Welterweight","date":"May 16, 2023","formattedDate":"2023-05","wasInTheFuture":true}},{"result":"Win","record":"7–0","opponentName":"Jack Grant","method":"Decision (unanimous)","event":"Cage Warriors 125","date":"June 26, 2021","round":"5","time":"5:00","location":"London, England","notes":"Won the Cage Warriors Welterweight Championship.","year":"2021","opponentInfoAtTheTime":0,"fighterRankAtTheTime":{"fighter":{"name":"Ian Machado Garry","rank":"13","link":"/wiki/Ian_Machado_Garry"},"division":"Welterweight","date":"May 16, 2023","formattedDate":"2023-05","wasInTheFuture":true}},{"result":"Win","record":"6–0","opponentName":"Rostem Akman","method":"KO (head kick)","event":"Cage Warriors 121","date":"March 19, 2021","round":"2","time":"2:28","location":"Liverpool, England","notes":"","year":"2021","opponentInfoAtTheTime":0,"fighterRankAtTheTime":{"fighter":{"name":"Ian Machado Garry","rank":"13","link":"/wiki/Ian_Machado_Garry"},"division":"Welterweight","date":"May 16, 2023","formattedDate":"2023-05","wasInTheFuture":true}},{"result":"Win","record":"5–0","opponentName":"Lawrence Jordan Tracey","method":"TKO (punches and elbows)","event":"Cage Warriors 119","date":"December 12, 2020","round":"1","time":"4:02","location":"London, England","notes":"","year":"2020","opponentInfoAtTheTime":0,"fighterRankAtTheTime":{"fighter":{"name":"Ian Machado Garry","rank":"13","link":"/wiki/Ian_Machado_Garry"},"division":"Welterweight","date":"May 16, 2023","formattedDate":"2023-05","wasInTheFuture":true}},{"result":"Win","record":"4–0","opponentName":"George McManus","method":"TKO (punches and head kick)","event":"Cage Warriors 115","date":"September 25, 2020","round":"2","time":"3:17","location":"Manchester, England","notes":"","year":"2020","opponentInfoAtTheTime":0,"fighterRankAtTheTime":{"fighter":{"name":"Ian Machado Garry","rank":"13","link":"/wiki/Ian_Machado_Garry"},"division":"Welterweight","date":"May 16, 2023","formattedDate":"2023-05","wasInTheFuture":true}},{"result":"Win","record":"3–0","opponentName":"Mateusz Figlak","method":"Technical Submission (rear-naked choke)","event":"Cage Warriors 110","date":"November 9, 2019","round":"1","time":"3:41","location":"Cork, Ireland","notes":"","year":"2019","opponentInfoAtTheTime":0,"fighterRankAtTheTime":{"fighter":{"name":"Ian Machado Garry","rank":"13","link":"/wiki/Ian_Machado_Garry"},"division":"Welterweight","date":"May 16, 2023","formattedDate":"2023-05","wasInTheFuture":true}},{"result":"Win","record":"2–0","opponentName":"Matteo Ceglia","method":"TKO (flying knee)","event":"Cage Warriors: Unplugged 2","date":"September 6, 2019","round":"2","time":"1:01","location":"London, England","notes":"Catchweight (177 lb) bout.","year":"2019","opponentInfoAtTheTime":0,"fighterRankAtTheTime":{"fighter":{"name":"Ian Machado Garry","rank":"13","link":"/wiki/Ian_Machado_Garry"},"division":"Welterweight","date":"May 16, 2023","formattedDate":"2023-05","wasInTheFuture":true}},{"result":"Win","record":"1–0","opponentName":"James Sheehan","method":"Decision (unanimous)","event":"Cage Warriors 101","date":"February 16, 2019","round":"3","time":"5:00","location":"Liverpool, England","notes":"Welterweight debut.","year":"2019","opponentInfoAtTheTime":0,"fighterRankAtTheTime":{"fighter":{"name":"Ian Machado Garry","rank":"13","link":"/wiki/Ian_Machado_Garry"},"division":"Welterweight","date":"May 16, 2023","formattedDate":"2023-05","wasInTheFuture":true}}],"recordString":""}