{"fighterInfo":{"wikiUrl":"https://en.wikipedia.org//wiki/Shamil_Gamzatov","name":"Shamil Gamzatov  Шамиль Гамзатов","ageFullString":" (1990-08-09) August 9, 1990 (age&#160;31)","age":"31","birthplace":"Kizlyar, Dagestan, Russian SFSR, Soviet Union","residence":"Makhachkala, Dagestan","nationality":"Russian","height":"1.87 m (6 ft 2 in)","weight":"218 lb (99 kg; 15.6 st)","division":"Light Heavyweight (205 lb) (2012 – present) Middleweight (185 lb) (2018)","reach":"76 in (193 cm)","style":"Brazilian Jiu-Jitsu, Sambo","fightingOutOf":"Makhachkala, Dagestan, Russia  Coconut Creek, Florida, U.S.","team":"Krepost ","teams":["Krepost "," Gorets MMA "," American Top Team"],"rank":"National Master of Sports in Sambo  Brown belt in Brazilian Jiu-Jitsu","yearsActive":"2012–present","totalFights":"15","wins":"14","knockoutWins":"1","submissionWins":"5","decisionWins":"4","losses":"1","relevantImages":["https://www.sherdog.com/image_crop/200/300/_images/fighter/20180705082239_Shamil_Gamzatov.JPG","https://fighttime.ru/images/fightbase/fighters/136875.jpg","https://24smi.org/public/media/celebrity/2020/04/28/do75kgtcffpj-shamil-gamzatov.jpg"]},"record":[{"result":"Loss","record":"14–1","opponentName":"Michał Oleksiejczuk","method":"TKO (punches)","event":"UFC 267","date":"October 30, 2021","round":"1","time":"3:31","location":"Abu Dhabi, United Arab Emirates","notes":"","year":"2021","opponentInfoAtTheTime":0},{"result":"Win","record":"14–0","opponentName":"Klidson Abreu","method":"Decision (split)","event":"UFC Fight Night: Magomedsharipov vs. Kattar","date":"November 9, 2019","round":"3","time":"5:00","location":"Moscow, Russia","notes":"Return to Light Heavyweight.","year":"2019","opponentInfoAtTheTime":0},{"result":"Win","record":"13–0","opponentName":"Rex Harris","method":"Decision (unanimous)","event":"PFL 6","date":"August 16, 2018","round":"3","time":"5:00","location":"Atlantic City, New Jersey, United States","notes":"2018 PFL Middleweight Tournament Opening Round.","year":"2018","opponentInfoAtTheTime":0},{"result":"Win","record":"12–0","opponentName":"Eddie Gordon","method":"Decision (unanimous)","event":"PFL 3","date":"July 5, 2018","round":"3","time":"5:00","location":"Washington, D.C., United States","notes":"Middleweight debut. 2018 PFL Middleweight Tournament Opening Round.","year":"2018","opponentInfoAtTheTime":0},{"result":"Win","record":"11–0","opponentName":"Rodney Wallace","method":"Decision (split)","event":"ACB 51","date":"January 13, 2017","round":"3","time":"5:00","location":"Irvine, California, United States","notes":"","year":"2017","opponentInfoAtTheTime":0},{"result":"Win","record":"10–0","opponentName":"Teddy Holder","method":"TKO (punches)","event":"WSOF 27","date":"January 23, 2016","round":"1","time":"2:32","location":"Memphis, Tennessee, United States","notes":"","year":"2016","opponentInfoAtTheTime":0},{"result":"Win","record":"9–0","opponentName":"Yuri Gorbenko","method":"Submission (triangle choke)","event":"N1 Pro: Nomad Pro MMA Cup 2014","date":"October 5, 2014","round":"1","time":"3:39","location":"Grozny, Russia","notes":"","year":"2014","opponentInfoAtTheTime":0},{"result":"Win","record":"8–0","opponentName":"Sukhrob Muradov","method":"TKO (punches)","event":"Fight Star: Saransk vs. Penza","date":"September 5, 2014","round":"1","time":"1:16","location":"Saransk, Russia","notes":"","year":"2014","opponentInfoAtTheTime":0},{"result":"Win","record":"7–0","opponentName":"Vladimir Mishchenko","method":"Submission (guillotine choke)","event":"Warriors Honor: Mayor's Cup","date":"December 4, 2013","round":"2","time":"2:07","location":"Kharkov, Ukraine","notes":"","year":"2013","opponentInfoAtTheTime":0},{"result":"Win","record":"6–0","opponentName":"Andrey Musanipov","method":"Submission (armbar)","event":"Battle of Champions 2","date":"August 25, 2013","round":"2","time":"1:14","location":"Ufa, Russia","notes":"","year":"2013","opponentInfoAtTheTime":0},{"result":"Win","record":"5–0","opponentName":"Ivan Fedunov","method":"KO (punch)","event":"Versia Fighting Championship 1","date":"August 17, 2013","round":"1","time":"3:52","location":"Pyatigorsk, Russia","notes":"Return to Light Heavyweight.","year":"2013","opponentInfoAtTheTime":0},{"result":"Win","record":"4–0","opponentName":"Ilya Gunenko","method":"Submission (armbar)","event":"WCSA Combat League: Combat Ring 3","date":"June 30, 2013","round":"1","time":"2:14","location":"Odessa, Ukraine","notes":"Heavyweight debut.","year":"2013","opponentInfoAtTheTime":0},{"result":"Win","record":"3–0","opponentName":"Rustam Omar-Ogly","method":"Submission (armbar)","event":"Derbent Fighting Championship","date":"July 13, 2012","round":"1","time":"3:40","location":"Derbent, Russia","notes":"","year":"2012","opponentInfoAtTheTime":0},{"result":"Win","record":"2–0","opponentName":"Assaad Raad","method":"TKO (punches)","event":"Top Fight: Battle of the Gyms","date":"February 25, 2012","round":"2","time":"2:35","location":"Dubai, United Arab Emirates","notes":"","year":"2012","opponentInfoAtTheTime":0},{"result":"Win","record":"1–0","opponentName":"Murat Aibazov","method":"TKO (punches)","event":"FoPoKC: Cup of Friendship","date":"January 30, 2012","round":"2","time":"1:35","location":"Teberda, Russia","notes":"Light Heavyweight debut.","year":"2012","opponentInfoAtTheTime":0}],"recordString":"","opponents":[]}